olx_web_scraper/__init__.py
olx_web_scraper/__main__.py
olx_web_scraper/utils/__init__.py
olx_web_scraper/utils/db.py
olx_web_scraper/utils/loader.py
olx_web_scraper/utils/parser.py
olx_web_scraper/utils/reader.py
olx_web_scraper/utils/uploader.py
olx_web_scraper/utils/writer.py
olx_web_scraper-0.2.2.dist-info/entry_points.txt
olx_web_scraper-0.2.2.dist-info/LICENSE.md
olx_web_scraper-0.2.2.dist-info/METADATA
olx_web_scraper-0.2.2.dist-info/WHEEL
olx_web_scraper-0.2.2.dist-info/RECORD
