Metadata-Version: 2.1
Name: olx-web-scraper
Version: 0.2.2
Summary: Use python to scrap for listings on olx.in based on search query.
License: MIT
Author: Akash NP
Author-email: akashnp1998@gmail.com
Requires-Python: >=3.8,<4.0
Classifier: License :: OSI Approved :: MIT License
Classifier: Programming Language :: Python :: 3
Classifier: Programming Language :: Python :: 3.8
Classifier: Programming Language :: Python :: 3.9
Classifier: Programming Language :: Python :: 3.10
Classifier: Programming Language :: Python :: 3.11
Requires-Dist: beautifulsoup4 (>=4.11.2,<5.0.0)
Requires-Dist: dnspython (>=2.3.0,<3.0.0)
Requires-Dist: pymongo (>=4.3.3,<5.0.0)
Requires-Dist: python-decouple (>=3.8,<4.0)
Requires-Dist: selenium (>=4.8.2,<5.0.0)
Requires-Dist: webdriver-manager (>=3.8.5,<4.0.0)
